README.md
setup.py
PyViO/__init__.py
PyViO/__main__.py
PyViO/interact.py
PyViO/methods.py
PyViO/visuals.py
PyViO.egg-info/PKG-INFO
PyViO.egg-info/SOURCES.txt
PyViO.egg-info/dependency_links.txt
PyViO.egg-info/requires.txt
PyViO.egg-info/top_level.txt
test/test_PyViO.py