Metadata-Version: 2.1
Name: PyViO
Version: 1.2.0
Summary: Visualize outliers in data
Home-page: UNKNOWN
Author: Team_PyViO
Author-email: team.pyvio@gmail.com
License: MIT
Platform: UNKNOWN
Classifier: License :: OSI Approved :: MIT License
Classifier: Programming Language :: Python :: 3
Classifier: Development Status :: 3 - Alpha
Classifier: Intended Audience :: Education
